{
	"scenario":"case_15",
	"skipped":false,
	"baselineSec":2.151e-3,
	"disjunctCount":10,
	"rows":[
		{
			"disjunctId":"{j[1, 2] == 0, j[2, 1] == 0}",
			"branchCount":2,
			"removeDelta":0.0,
			"removeTag":"Matches",
			"forceResults":[
				{
					"branch":"j[1, 2] == 0",
					"delta":0.0,
					"tag":"Matches"
				},
				{
					"branch":"j[2, 1] == 0",
					"delta":0.0,
					"tag":"Matches"
				}
			]
		},
		{
			"disjunctId":"{j[1, 3] == 0, j[3, 1] == 0}",
			"branchCount":2,
			"removeDelta":0.0,
			"removeTag":"Matches",
			"forceResults":[
				{
					"branch":"j[1, 3] == 0",
					"delta":0.0,
					"tag":"Matches"
				},
				{
					"branch":"j[3, 1] == 0",
					"delta":0.0,
					"tag":"Matches"
				}
			]
		},
		{
			"disjunctId":"{j[2, 1, 3] == 0, j[3, 1, 2] == 0}",
			"branchCount":2,
			"removeDelta":0.0,
			"removeTag":"Matches",
			"forceResults":[
				{
					"branch":"j[2, 1, 3] == 0",
					"delta":0.0,
					"tag":"Matches"
				},
				{
					"branch":"j[3, 1, 2] == 0",
					"delta":0.0,
					"tag":"Matches"
				}
			]
		},
		{
			"disjunctId":"{j[2, 1, \"auxExit1\"] == 0, -u[2, 1] + u[\"auxExit1\", 1] == 0}",
			"branchCount":2,
			"removeDelta":0.0,
			"removeTag":"Matches",
			"forceResults":[
				{
					"branch":"j[2, 1, \"auxExit1\"] == 0",
					"delta":0.0,
					"tag":"Matches"
				},
				{
					"branch":"-u[2, 1] + u[\"auxExit1\", 1] == 0",
					"delta":0.0,
					"tag":"Matches"
				}
			]
		},
		{
			"disjunctId":"{j[2, 1, 3] == 0, 2 - u[2, 1] + u[3, 1] == 0}",
			"branchCount":2,
			"removeDelta":0.0,
			"removeTag":"Matches",
			"forceResults":[
				{
					"branch":"j[2, 1, 3] == 0",
					"delta":0.0,
					"tag":"Matches"
				},
				{
					"branch":"2 - u[2, 1] + u[3, 1] == 0",
					"delta":0.0,
					"tag":"Matches"
				}
			]
		},
		{
			"disjunctId":"{j[3, 1, \"auxExit1\"] == 0, -u[3, 1] + u[\"auxExit1\", 1] == 0}",
			"branchCount":2,
			"removeDelta":0.0,
			"removeTag":"Matches",
			"forceResults":[
				{
					"branch":"j[3, 1, \"auxExit1\"] == 0",
					"delta":0.0,
					"tag":"Matches"
				},
				{
					"branch":"-u[3, 1] + u[\"auxExit1\", 1] == 0",
					"delta":0.0,
					"tag":"Matches"
				}
			]
		},
		{
			"disjunctId":"{j[3, 1, 2] == 0, 1 + u[2, 1] - u[3, 1] == 0}",
			"branchCount":2,
			"removeDelta":0.0,
			"removeTag":"Matches",
			"forceResults":[
				{
					"branch":"j[3, 1, 2] == 0",
					"delta":0.0,
					"tag":"Matches"
				},
				{
					"branch":"1 + u[2, 1] - u[3, 1] == 0",
					"delta":0.0,
					"tag":"Matches"
				}
			]
		},
		{
			"disjunctId":"{j[\"auxEntry2\", 2, 1] == 0, u[1, 2] - u[\"auxEntry2\", 2] == 0}",
			"branchCount":2,
			"removeDelta":0.0,
			"removeTag":"Matches",
			"forceResults":[
				{
					"branch":"j[\"auxEntry2\", 2, 1] == 0",
					"delta":0.0,
					"tag":"Matches"
				},
				{
					"branch":"u[1, 2] - u[\"auxEntry2\", 2] == 0",
					"delta":0.0,
					"tag":"Matches"
				}
			]
		},
		{
			"disjunctId":"{j[\"auxEntry3\", 3, 1] == 0, u[1, 3] - u[\"auxEntry3\", 3] == 0}",
			"branchCount":2,
			"removeDelta":0.0,
			"removeTag":"Matches",
			"forceResults":[
				{
					"branch":"j[\"auxEntry3\", 3, 1] == 0",
					"delta":0.0,
					"tag":"Matches"
				},
				{
					"branch":"u[1, 3] - u[\"auxEntry3\", 3] == 0",
					"delta":0.0,
					"tag":"Matches"
				}
			]
		},
		{
			"disjunctId":"{j[1, \"auxExit1\"] == 0, u[\"auxExit1\", 1] == 0}",
			"branchCount":2,
			"removeDelta":0.0,
			"removeTag":"Matches",
			"forceResults":[
				{
					"branch":"j[1, \"auxExit1\"] == 0",
					"delta":0.0,
					"tag":"Matches"
				},
				{
					"branch":"u[\"auxExit1\", 1] == 0",
					"delta":0.0,
					"tag":"Matches"
				}
			]
		}
	]
}